README.rst
setup.py
katalin/__init__.py
katalin/version.py
katalin.egg-info/PKG-INFO
katalin.egg-info/SOURCES.txt
katalin.egg-info/dependency_links.txt
katalin.egg-info/requires.txt
katalin.egg-info/top_level.txt